tadaaa/__init__.py
tadaaa/tada.py
tadaaa-0.0.4.dist-info/METADATA
tadaaa-0.0.4.dist-info/WHEEL
tadaaa-0.0.4.dist-info/top_level.txt
tadaaa-0.0.4.dist-info/RECORD
